{"last-updated": "16:26 18-05-2021", "leaders": {"labels": ["Esther Ouwehand", "Kees van der Staaij", "Lilianne Ploumen", "Gert-Jan Segers", "Wopke Hoekstra", "Mark Rutte", "Sigrid Kaag", "Geert Wilders", "Lilian Marijnissen", "Jesse Klaver", "Liane  Haan", "Farid Azarkan", "Thierry Baudet", "Sylvana Simons", "Laurens Dassen", "Caroline Plas", "Joost Eerdmans", "Pieter Omtzigt"], "data": [0, 0, 0, 0, 0, 0, 0, 0, 0, 0, 0, 0, 0, 0, 0, 8, 0, 0]}, "occurrences-total": {"labels": ["platteland", "boerburgerbeweging", "boeren", "politiek", "leefbaarheid", "dorpen", "nederland", "bekijk", "staat", "grijs"], "data": [226, 76, 52, 43, 41, 41, 41, 39, 38, 36]}, "impressions-total": {"labels": ["platteland", "boerburgerbeweging", "nederland", "waar", "boeren", "dorpen", "leefbaarheid", "grijs", "staat", "mega-zonneparken"], "data": [25176387.0, 7271462.0, 6051980.0, 5279984.0, 5047474.0, 4027480.0, 3952480.0, 3844982.0, 3822481.0, 3799982.0]}, "potential-reach-total": {"labels": ["platteland", "boerburgerbeweging", "boeren", "nederland", "waar", "politiek", "zich", "staat", "leefbaarheid", "komen"], "data": [133450162.0, 51335057.0, 44850044.0, 34430035.0, 27050028.0, 22475028.0, 21475022.0, 19325024.0, 18400026.0, 17250020.0]}, "occurrences-male": {"labels": ["platteland", "boerburgerbeweging", "boeren", "politiek", "leefbaarheid", "dorpen", "nederland", "bekijk", "staat", "grijs"], "data": [226, 76, 52, 43, 41, 41, 41, 39, 38, 36]}, "impressions-male": {"labels": ["platteland", "boerburgerbeweging", "nederland", "boeren", "waar", "zorgen", "femke", "politiek", "grijs", "dorpen"], "data": [15073014.0, 4881887.0, 4112627.0, 3410559.0, 3393088.0, 2407231.0, 2366293.0, 2241311.0, 2200427.0, 2193817.0]}, "potential-reach-male": {"labels": ["platteland", "boerburgerbeweging", "boeren", "nederland", "waar", "zich", "politiek", "grote", "komen", "staat"], "data": [82799897.0, 33322724.0, 30781908.0, 22589963.0, 17689929.0, 15131497.0, 14707082.0, 11742255.0, 11679950.0, 11509183.0]}, "occurrences-female": {"labels": ["platteland", "boerburgerbeweging", "boeren", "politiek", "leefbaarheid", "dorpen", "nederland", "bekijk", "staat", "grijs"], "data": [226, 76, 52, 43, 41, 41, 41, 39, 38, 36]}, "impressions-female": {"labels": ["platteland", "boerburgerbeweging", "nederland", "waar", "dorpen", "leefbaarheid", "mega-zonneparken", "grijs", "staat", "boeren"], "data": [10042605.0, 2372636.0, 1925853.0, 1874850.0, 1823614.0, 1765092.0, 1637848.0, 1634819.0, 1629454.0, 1625704.0]}, "potential-reach-female": {"labels": ["platteland", "boerburgerbeweging", "boeren", "nederland", "waar", "leefbaarheid", "staat", "politiek", "dorpen", "mega-zonneparken"], "data": [50347324.0, 17888705.0, 13974485.0, 11760763.0, 9299776.0, 8122844.0, 7767925.0, 7715535.0, 7359461.0, 6912110.0]}, "occurrences-13-17": {"labels": ["platteland", "boerburgerbeweging", "boeren", "politiek", "leefbaarheid", "dorpen", "nederland", "bekijk", "staat", "grijs"], "data": [226, 76, 52, 43, 41, 41, 41, 39, 38, 36]}, "impressions-13-17": {"labels": ["platteland", "leefbaarheid", "boerennatuur", "belangrijk", "dorpen", "datacenters", "mega-zonneparken", "politiek", "bossen", "boerburgerbeweging"], "data": [481.0, 123.0, 112.0, 112.0, 111.0, 108.0, 106.0, 105.0, 105.0, 103.0]}, "potential-reach-13-17": {"labels": ["platteland", "leefbaarheid", "dorpen", "datacenters", "boerennatuur", "belangrijk", "politiek", "mega-zonneparken", "boerburgerbeweging", "bossen"], "data": [1917.0, 495.0, 467.0, 460.0, 456.0, 456.0, 443.0, 439.0, 437.0, 434.0]}, "occurrences-18-24": {"labels": ["platteland", "boerburgerbeweging", "boeren", "politiek", "leefbaarheid", "dorpen", "nederland", "bekijk", "staat", "grijs"], "data": [226, 76, 52, 43, 41, 41, 41, 39, 38, 36]}, "impressions-18-24": {"labels": ["platteland", "boerburgerbeweging", "nederland", "dorpen", "leefbaarheid", "boeren", "waar", "politiek", "mega-zonneparken", "grijs"], "data": [4559877.0, 1312040.0, 895336.0, 796713.0, 785803.0, 765955.0, 763168.0, 714129.0, 704013.0, 700411.0]}, "potential-reach-18-24": {"labels": ["platteland", "boerburgerbeweging", "boeren", "nederland", "politiek", "waar", "leefbaarheid", "zich", "belangrijk", "bekijk"], "data": [26438663.0, 9461072.0, 8930750.0, 6195888.0, 4695067.0, 4556530.0, 3921896.0, 3918546.0, 3554600.0, 3510288.0]}, "occurrences-25-34": {"labels": ["platteland", "boerburgerbeweging", "boeren", "politiek", "leefbaarheid", "dorpen", "nederland", "bekijk", "staat", "grijs"], "data": [226, 76, 52, 43, 41, 41, 41, 39, 38, 36]}, "impressions-25-34": {"labels": ["platteland", "boerburgerbeweging", "nederland", "boeren", "waar", "dorpen", "leefbaarheid", "politiek", "grijs", "mega-zonneparken"], "data": [5822553.0, 1809983.0, 1372208.0, 1136473.0, 1130159.0, 980579.0, 943709.0, 914017.0, 908280.0, 897030.0]}, "potential-reach-25-34": {"labels": ["platteland", "boerburgerbeweging", "boeren", "nederland", "waar", "politiek", "staat", "leefbaarheid", "bekijk", "dorpen"], "data": [28271042.0, 9963068.0, 7886775.0, 6814495.0, 5256777.0, 4785584.0, 4131593.0, 4126847.0, 3932420.0, 3883332.0]}, "occurrences-35-44": {"labels": ["platteland", "boerburgerbeweging", "boeren", "politiek", "leefbaarheid", "dorpen", "nederland", "bekijk", "staat", "grijs"], "data": [226, 76, 52, 43, 41, 41, 41, 39, 38, 36]}, "impressions-35-44": {"labels": ["platteland", "boerburgerbeweging", "nederland", "waar", "boeren", "dorpen", "leefbaarheid", "zorgen", "grijs", "mega-zonneparken"], "data": [4202995.0, 1324695.0, 1050689.0, 882783.0, 878855.0, 680566.0, 655770.0, 650799.0, 649269.0, 639565.0]}, "potential-reach-35-44": {"labels": ["platteland", "boerburgerbeweging", "boeren", "nederland", "waar", "politiek", "zich", "staat", "leefbaarheid", "grijs"], "data": [19901977.0, 7309669.0, 5764048.0, 4885076.0, 3929006.0, 3325137.0, 2977289.0, 2948560.0, 2767950.0, 2738459.0]}, "occurrences-45-54": {"labels": ["platteland", "boerburgerbeweging", "boeren", "politiek", "leefbaarheid", "dorpen", "nederland", "bekijk", "staat", "grijs"], "data": [226, 76, 52, 43, 41, 41, 41, 39, 38, 36]}, "impressions-45-54": {"labels": ["platteland", "boerburgerbeweging", "nederland", "waar", "boeren", "zorgen", "dorpen", "grijs", "leefbaarheid", "mega-zonneparken"], "data": [4623969.0, 1240482.0, 1190452.0, 1058391.0, 895932.0, 732928.0, 706726.0, 702606.0, 690678.0, 690149.0]}, "potential-reach-45-54": {"labels": ["platteland", "boerburgerbeweging", "boeren", "nederland", "waar", "zich", "politiek", "staat", "komen", "peilingen"], "data": [22519735.0, 7946298.0, 6810725.0, 5937911.0, 4831283.0, 3711359.0, 3673072.0, 3276706.0, 3099442.0, 3027197.0]}, "occurrences-55-64": {"labels": ["platteland", "boerburgerbeweging", "boeren", "politiek", "leefbaarheid", "dorpen", "nederland", "bekijk", "staat", "grijs"], "data": [226, 76, 52, 43, 41, 41, 41, 39, 38, 36]}, "impressions-55-64": {"labels": ["platteland", "nederland", "waar", "boerburgerbeweging", "boeren", "zorgen", "staat", "grijs", "mega-zonneparken", "dorpen"], "data": [4023989.0, 1058881.0, 1011461.0, 973238.0, 841736.0, 651773.0, 595335.0, 593227.0, 584637.0, 584338.0]}, "potential-reach-55-64": {"labels": ["platteland", "boerburgerbeweging", "boeren", "nederland", "waar", "zich", "politiek", "staat", "haag", "komen"], "data": [20650797.0, 7877137.0, 7456316.0, 5886083.0, 4815531.0, 3729911.0, 3286212.0, 3038338.0, 2895230.0, 2880803.0]}, "occurrences-65+": {"labels": ["platteland", "boerburgerbeweging", "boeren", "politiek", "leefbaarheid", "dorpen", "nederland", "bekijk", "staat", "grijs"], "data": [226, 76, 52, 43, 41, 41, 41, 39, 38, 36]}, "impressions-65+": {"labels": ["platteland", "boerburgerbeweging", "boeren", "nederland", "waar", "staat", "leefbaarheid", "bekijk", "groen", "grijs"], "data": [1940121.0, 610327.0, 528475.0, 484318.0, 433913.0, 320008.0, 292720.0, 291341.0, 290576.0, 290576.0]}, "potential-reach-65+": {"labels": ["platteland", "boerburgerbeweging", "boeren", "nederland", "waar", "haag", "zich", "burgers", "politiek", "programma"], "data": [15655533.0, 8771880.0, 8000388.0, 4708858.0, 3659641.0, 3320334.0, 3306195.0, 2736334.0, 2706360.0, 2564197.0]}, "occurrences-drenthe": {"labels": ["platteland", "boerburgerbeweging", "boeren", "politiek", "leefbaarheid", "dorpen", "nederland", "bekijk", "staat", "grijs"], "data": [226, 76, 52, 43, 41, 41, 41, 39, 38, 36]}, "impressions-drenthe": {"labels": ["platteland", "boerburgerbeweging", "nederland", "waar", "zorgen", "leefbaarheid", "boeren", "ruimte", "staat", "grijs"], "data": [1841759.0, 429261.0, 389576.0, 336628.0, 305987.0, 300721.0, 290437.0, 260126.0, 224556.0, 223521.0]}, "potential-reach-drenthe": {"labels": ["platteland", "boerburgerbeweging", "boeren", "nederland", "waar", "politiek", "zich", "leefbaarheid", "ruimte", "komen"], "data": [9046483.0, 2880410.0, 2749325.0, 2161964.0, 1663354.0, 1365452.0, 1302466.0, 1240635.0, 1234500.0, 1219138.0]}, "occurrences-flevoland": {"labels": ["platteland", "boerburgerbeweging", "boeren", "politiek", "leefbaarheid", "dorpen", "nederland", "bekijk", "staat", "grijs"], "data": [226, 76, 52, 43, 41, 41, 41, 39, 38, 36]}, "impressions-flevoland": {"labels": ["platteland", "nederland", "boerburgerbeweging", "waar", "boeren", "ruimte", "zorgen", "lelystad", "plaats", "voedselmakers"], "data": [477694.0, 166722.0, 158512.0, 129737.0, 111104.0, 87070.0, 83664.0, 76408.0, 73960.0, 71097.0]}, "potential-reach-flevoland": {"labels": ["platteland", "boerburgerbeweging", "nederland", "boeren", "waar", "lelystad", "ruimte", "vliegveld", "zich", "politiek"], "data": [2609911.0, 1038168.0, 903489.0, 892708.0, 616990.0, 515110.0, 503220.0, 416774.0, 401803.0, 395151.0]}, "occurrences-friesland": {"labels": ["platteland", "boerburgerbeweging", "boeren", "politiek", "leefbaarheid", "dorpen", "nederland", "bekijk", "staat", "grijs"], "data": [226, 76, 52, 43, 41, 41, 41, 39, 38, 36]}, "impressions-friesland": {"labels": ["platteland", "femke", "boerburgerbeweging", "nederland", "waar", "boeren", "zorgen", "politiek", "grijs", "staat"], "data": [1825822.0, 582819.0, 569527.0, 513020.0, 455561.0, 395509.0, 300289.0, 282783.0, 276135.0, 275324.0]}, "potential-reach-friesland": {"labels": ["platteland", "boerburgerbeweging", "boeren", "femke", "nederland", "waar", "politiek", "zich", "grote", "politieke"], "data": [9987411.0, 3664662.0, 3550112.0, 2940477.0, 2714108.0, 2216670.0, 1936778.0, 1737475.0, 1616156.0, 1511607.0]}, "occurrences-gelderland": {"labels": ["platteland", "boerburgerbeweging", "boeren", "politiek", "leefbaarheid", "dorpen", "nederland", "bekijk", "staat", "grijs"], "data": [226, 76, 52, 43, 41, 41, 41, 39, 38, 36]}, "impressions-gelderland": {"labels": ["platteland", "boerburgerbeweging", "nederland", "waar", "boeren", "dorpen", "leefbaarheid", "grijs", "staat", "zorgen"], "data": [4357586.0, 1125513.0, 1014188.0, 889242.0, 728863.0, 682869.0, 631958.0, 608255.0, 606969.0, 597844.0]}, "potential-reach-gelderland": {"labels": ["platteland", "boerburgerbeweging", "boeren", "nederland", "waar", "zich", "politiek", "haag", "laten", "verkiezingsprogramma"], "data": [22015257.0, 7117849.0, 5809071.0, 5366220.0, 4060558.0, 3901831.0, 3373676.0, 3166156.0, 3048812.0, 2980480.0]}, "occurrences-groningen": {"labels": ["platteland", "boerburgerbeweging", "boeren", "politiek", "leefbaarheid", "dorpen", "nederland", "bekijk", "staat", "grijs"], "data": [226, 76, 52, 43, 41, 41, 41, 39, 38, 36]}, "impressions-groningen": {"labels": ["platteland", "boerburgerbeweging", "nederland", "waar", "leefbaarheid", "boeren", "dorpen", "kleine", "staat", "grijs"], "data": [1288263.0, 377611.0, 321907.0, 283931.0, 260683.0, 256733.0, 251829.0, 226833.0, 193275.0, 190921.0]}, "potential-reach-groningen": {"labels": ["platteland", "boeren", "boerburgerbeweging", "nederland", "waar", "politiek", "zich", "leefbaarheid", "staat", "kleine"], "data": [7265804.0, 2696563.0, 2658485.0, 1888656.0, 1531279.0, 1349888.0, 1261501.0, 1197271.0, 1008780.0, 981546.0]}, "occurrences-limburg": {"labels": ["platteland", "boerburgerbeweging", "boeren", "politiek", "leefbaarheid", "dorpen", "nederland", "bekijk", "staat", "grijs"], "data": [226, 76, 52, 43, 41, 41, 41, 39, 38, 36]}, "impressions-limburg": {"labels": ["platteland", "boerburgerbeweging", "nederland", "boeren", "waar", "frank", "dorpen", "mega-zonneparken", "bekijk", "leefbaarheid"], "data": [1757162.0, 571690.0, 447624.0, 404722.0, 395167.0, 350729.0, 339519.0, 336888.0, 310567.0, 283039.0]}, "potential-reach-limburg": {"labels": ["platteland", "frank", "boerburgerbeweging", "boeren", "bekijk", "ervoor", "boer", "jaar", "vraag", "graag"], "data": [9477282.0, 8080321.0, 6335238.0, 4469852.0, 3980117.0, 3818386.0, 3533342.0, 3181623.0, 3121766.0, 3070846.0]}, "occurrences-noord-brabant": {"labels": ["platteland", "boerburgerbeweging", "boeren", "politiek", "leefbaarheid", "dorpen", "nederland", "bekijk", "staat", "grijs"], "data": [226, 76, 52, 43, 41, 41, 41, 39, 38, 36]}, "impressions-noord-brabant": {"labels": ["platteland", "boerburgerbeweging", "nederland", "dorpen", "waar", "boeren", "mega-zonneparken", "leefbaarheid", "grijs", "zorgen"], "data": [3797045.0, 1044436.0, 870868.0, 822569.0, 774909.0, 762536.0, 647453.0, 628813.0, 605293.0, 599956.0]}, "potential-reach-noord-brabant": {"labels": ["platteland", "boerburgerbeweging", "boeren", "nederland", "waar", "dorpen", "politiek", "leefbaarheid", "staat", "mega-zonneparken"], "data": [18938903.0, 6387873.0, 5185894.0, 4475301.0, 3589409.0, 3409700.0, 2937437.0, 2836463.0, 2695660.0, 2688043.0]}, "occurrences-noord-holland": {"labels": ["platteland", "boerburgerbeweging", "boeren", "politiek", "leefbaarheid", "dorpen", "nederland", "bekijk", "staat", "grijs"], "data": [226, 76, 52, 43, 41, 41, 41, 39, 38, 36]}, "impressions-noord-holland": {"labels": ["platteland", "boeren", "boerburgerbeweging", "nederland", "waar", "staat", "grijs", "groen", "overheid", "grond"], "data": [1658361.0, 818364.0, 596995.0, 526942.0, 444807.0, 398609.0, 392867.0, 385043.0, 356451.0, 356188.0]}, "potential-reach-noord-holland": {"labels": ["platteland", "boeren", "boerburgerbeweging", "nederland", "krijgen", "grond", "waar", "staat", "tweede", "programma"], "data": [10556839.0, 7119367.0, 4671735.0, 3486765.0, 3169691.0, 2764775.0, 2729120.0, 2712699.0, 2535167.0, 2491403.0]}, "occurrences-overijssel": {"labels": ["platteland", "boerburgerbeweging", "boeren", "politiek", "leefbaarheid", "dorpen", "nederland", "bekijk", "staat", "grijs"], "data": [226, 76, 52, 43, 41, 41, 41, 39, 38, 36]}, "impressions-overijssel": {"labels": ["platteland", "boerburgerbeweging", "nederland", "waar", "dorpen", "politiek", "boeren", "leefbaarheid", "grijs", "staat"], "data": [3801210.0, 980004.0, 891347.0, 714750.0, 609772.0, 601355.0, 579342.0, 563700.0, 560948.0, 559875.0]}, "potential-reach-overijssel": {"labels": ["platteland", "boerburgerbeweging", "boeren", "nederland", "politiek", "waar", "zich", "staat", "leefbaarheid", "altijd"], "data": [19345395.0, 6134401.0, 5081807.0, 4738798.0, 3534027.0, 3317866.0, 2807132.0, 2716880.0, 2590731.0, 2500119.0]}, "occurrences-utrecht": {"labels": ["platteland", "boerburgerbeweging", "boeren", "politiek", "leefbaarheid", "dorpen", "nederland", "bekijk", "staat", "grijs"], "data": [226, 76, 52, 43, 41, 41, 41, 39, 38, 36]}, "impressions-utrecht": {"labels": ["platteland", "boerburgerbeweging", "nederland", "politiek", "leefbaarheid", "waar", "staat", "mega-zonneparken", "grijs", "groen"], "data": [1547074.0, 389842.0, 293724.0, 291980.0, 268613.0, 267659.0, 260380.0, 257336.0, 256843.0, 252867.0]}, "potential-reach-utrecht": {"labels": ["platteland", "boerburgerbeweging", "boeren", "nederland", "politiek", "waar", "leefbaarheid", "staat", "inwoners", "mega-zonneparken"], "data": [7562521.0, 2422765.0, 1920773.0, 1709142.0, 1570486.0, 1317219.0, 1205958.0, 1188349.0, 1099325.0, 1056386.0]}, "occurrences-zeeland": {"labels": ["platteland", "boerburgerbeweging", "boeren", "politiek", "leefbaarheid", "dorpen", "nederland", "bekijk", "staat", "grijs"], "data": [226, 76, 52, 43, 41, 41, 41, 39, 38, 36]}, "impressions-zeeland": {"labels": ["platteland", "waar", "boerburgerbeweging", "staan", "zeeuwse", "overheid", "zeeland", "zullen", "arno", "kandidaten"], "data": [1187279.0, 368579.0, 344027.0, 339483.0, 333707.0, 306622.0, 298148.0, 290647.0, 251563.0, 249371.0]}, "potential-reach-zeeland": {"labels": ["platteland", "staan", "boerburgerbeweging", "waar", "zeeuwse", "zullen", "zeeland", "hanse", "vael", "overheid"], "data": [5671731.0, 2298798.0, 2231452.0, 2211523.0, 2202388.0, 2127689.0, 1911855.0, 1837370.0, 1808706.0, 1736105.0]}, "occurrences-zuid-holland": {"labels": ["platteland", "boerburgerbeweging", "boeren", "politiek", "leefbaarheid", "dorpen", "nederland", "bekijk", "staat", "grijs"], "data": [226, 76, 52, 43, 41, 41, 41, 39, 38, 36]}, "impressions-zuid-holland": {"labels": ["platteland", "boerburgerbeweging", "nederland", "boeren", "femke", "leefbaarheid", "belangrijk", "bekijk", "tweede", "politiek"], "data": [1630877.0, 682433.0, 401533.0, 345404.0, 287468.0, 275424.0, 263307.0, 258496.0, 253777.0, 248232.0]}, "potential-reach-zuid-holland": {"labels": ["platteland", "boerburgerbeweging", "boeren", "nederland", "zich", "politiek", "waar", "burgers", "haag", "goed"], "data": [10946748.0, 5785138.0, 4315136.0, 3337705.0, 1949670.0, 1936266.0, 1846963.0, 1762657.0, 1659062.0, 1631543.0]}}