{"last-updated": "15:35 01-06-2021", "occurrences-leaders": {"labels": ["Lilianne Ploumen", "Wopke Hoekstra", "Mark Rutte", "Sigrid Kaag", "Geert Wilders", "Jesse Klaver", "Thierry Baudet"], "data": [1, 4, 20, 2, 10, 39, 4]}, "impressions-leaders": {"labels": ["Lilianne Ploumen", "Wopke Hoekstra", "Mark Rutte", "Sigrid Kaag", "Geert Wilders", "Jesse Klaver", "Thierry Baudet"], "data": [225000, 339998, 2247490, 412499, 384995, 2762480, 325998]}, "potential-reach-leaders": {"labels": ["Lilianne Ploumen", "Wopke Hoekstra", "Mark Rutte", "Sigrid Kaag", "Geert Wilders", "Jesse Klaver", "Thierry Baudet"], "data": [1000001, 3050003, 15875014, 2000002, 3450005, 18505022, 2100002]}, "occurrences-total": {"labels": ["groenlinks", "nederland", "samen", "tijd", "#meertoekomst", "tweede", "jaar", "#meergroenlinks", "idee", "samenleving"], "data": [477, 183, 111, 111, 110, 107, 106, 99, 94, 84]}, "impressions-total": {"labels": ["groenlinks", "nederland", "#meergroenlinks", "#meertoekomst", "tijd", "kabinet", "samen", "iets", "plannen", "laten"], "data": [14051262, 10879908, 5863950, 5375945, 5315944, 5306460, 4504444, 4252464, 4145474, 4133962]}, "potential-reach-total": {"labels": ["groenlinks", "nederland", "tijd", "#meertoekomst", "#meergroenlinks", "samen", "laten", "jaar", "klimaat", "kabinet"], "data": [180597776, 94523712, 61030121, 55770565, 52524058, 46066714, 44023049, 41933661, 41572542, 41016648]}, "occurrences-female": {"labels": ["groenlinks", "nederland", "samen", "tijd", "#meertoekomst", "tweede", "jaar", "#meergroenlinks", "idee", "samenleving"], "data": [477, 183, 111, 111, 110, 107, 106, 99, 94, 84]}, "impressions-female": {"labels": ["groenlinks", "nederland", "#meergroenlinks", "#meertoekomst", "tijd", "kabinet", "samen", "iets", "klimaat", "plannen"], "data": [7225796, 5542315, 3686214, 3416239, 3234868, 2630904, 2397247, 2300901, 2294900, 2260778]}, "potential-reach-female": {"labels": ["groenlinks", "nederland", "tijd", "#meertoekomst", "#meergroenlinks", "stemmen", "idee", "samen", "jaar", "klimaat"], "data": [98598899, 51372041, 33810345, 33750054, 31475889, 26340409, 26229070, 25787582, 24515372, 23989774]}, "occurrences-male": {"labels": ["groenlinks", "nederland", "samen", "tijd", "#meertoekomst", "tweede", "jaar", "#meergroenlinks", "idee", "samenleving"], "data": [477, 183, 111, 111, 110, 107, 106, 99, 94, 84]}, "impressions-male": {"labels": ["groenlinks", "nederland", "kabinet", "#meergroenlinks", "samen", "tijd", "laten", "#meertoekomst", "iets", "plannen"], "data": [6766298, 5291221, 2658080, 2148748, 2085814, 2059475, 2003688, 1931899, 1930764, 1866875]}, "potential-reach-male": {"labels": ["groenlinks", "nederland", "tijd", "#meertoekomst", "laten", "#meergroenlinks", "samen", "kabinet", "tweede", "tegen"], "data": [81064813, 42640139, 26899653, 21665618, 21197833, 20753990, 19981575, 18943897, 18612719, 17813892]}, "occurrences-13-17": {"labels": ["groenlinks", "nederland", "samen", "tijd", "#meertoekomst", "tweede", "jaar", "#meergroenlinks", "idee", "samenleving"], "data": [477, 183, 111, 111, 110, 107, 106, 99, 94, 84]}, "impressions-13-17": {"labels": ["groenlinks", "stemmen", "onder", "renkum", "dwars", "achter", "dwarsdenken", "raadslid", "zelf", "waarom"], "data": [30393, 28372, 19428, 18858, 12838, 12415, 11157, 10162, 10037, 9669]}, "potential-reach-13-17": {"labels": ["groenlinks", "stemmen", "zuid-holland", "weidevogels", "onder", "renkum", "vroeger", "scholekster", "actieplan", "openbaar"], "data": [6099190, 2264392, 2053050, 1851362, 1677342, 1508722, 1292887, 1291813, 1173300, 993706]}, "occurrences-18-24": {"labels": ["groenlinks", "nederland", "samen", "tijd", "#meertoekomst", "tweede", "jaar", "#meergroenlinks", "idee", "samenleving"], "data": [477, 183, 111, 111, 110, 107, 106, 99, 94, 84]}, "impressions-18-24": {"labels": ["groenlinks", "nederland", "#meergroenlinks", "#meertoekomst", "stemmen", "tijd", "samen", "iets", "#linkinbio", "woningen"], "data": [2603560, 1787391, 1733929, 1600631, 1011866, 981132, 930646, 905020, 846490, 797887]}, "potential-reach-18-24": {"labels": ["groenlinks", "nederland", "#meertoekomst", "tijd", "#meergroenlinks", "stemmen", "samen", "idee", "toekomst", "tweede"], "data": [56401628, 25017436, 19221437, 18113195, 17184919, 14408870, 14308733, 14170496, 13559361, 12667780]}, "occurrences-25-34": {"labels": ["groenlinks", "nederland", "samen", "tijd", "#meertoekomst", "tweede", "jaar", "#meergroenlinks", "idee", "samenleving"], "data": [477, 183, 111, 111, 110, 107, 106, 99, 94, 84]}, "impressions-25-34": {"labels": ["groenlinks", "nederland", "#meergroenlinks", "#meertoekomst", "samen", "stemmen", "iets", "tijd", "laten", "woningen"], "data": [3943917, 2786300, 2050084, 1834521, 1229629, 1163540, 1124625, 1123191, 1059402, 994546]}, "potential-reach-25-34": {"labels": ["groenlinks", "nederland", "#meertoekomst", "#meergroenlinks", "tijd", "stemmen", "samen", "idee", "laten", "toekomst"], "data": [45424032, 25084485, 18733449, 18115932, 13888378, 13473847, 12508077, 11409813, 10844357, 10594635]}, "occurrences-35-44": {"labels": ["groenlinks", "nederland", "samen", "tijd", "#meertoekomst", "tweede", "jaar", "#meergroenlinks", "idee", "samenleving"], "data": [477, 183, 111, 111, 110, 107, 106, 99, 94, 84]}, "impressions-35-44": {"labels": ["groenlinks", "nederland", "samen", "plannen", "iets", "#meergroenlinks", "#meertoekomst", "tijd", "iedereen", "laat"], "data": [1979163, 1523977, 678233, 664438, 651658, 622591, 604626, 589571, 530658, 526738]}, "potential-reach-35-44": {"labels": ["groenlinks", "nederland", "#meertoekomst", "tijd", "#meergroenlinks", "samen", "laten", "alleen", "nieuwe", "jaar"], "data": [16377986, 10229786, 5449763, 5300863, 5219372, 4773615, 4489863, 4202624, 4112255, 3969688]}, "occurrences-45-54": {"labels": ["groenlinks", "nederland", "samen", "tijd", "#meertoekomst", "tweede", "jaar", "#meergroenlinks", "idee", "samenleving"], "data": [477, 183, 111, 111, 110, 107, 106, 99, 94, 84]}, "impressions-45-54": {"labels": ["nederland", "groenlinks", "kabinet", "tijd", "natuur", "klimaat", "zich", "laten", "zorgen", "jaar"], "data": [2538118, 2484716, 1893470, 1250709, 1040399, 1026713, 1023804, 1021395, 1003865, 938956]}, "potential-reach-45-54": {"labels": ["groenlinks", "nederland", "kabinet", "tijd", "natuur", "laten", "jaar", "dieren", "komt", "klimaat"], "data": [22112533, 17978738, 13314123, 9974696, 9744157, 9113843, 8783617, 8317870, 8165474, 7951448]}, "occurrences-55-64": {"labels": ["groenlinks", "nederland", "samen", "tijd", "#meertoekomst", "tweede", "jaar", "#meergroenlinks", "idee", "samenleving"], "data": [477, 183, 111, 111, 110, 107, 106, 99, 94, 84]}, "impressions-55-64": {"labels": ["groenlinks", "nederland", "kabinet", "tijd", "plannen", "laten", "klimaat", "natuur", "zich", "zorgen"], "data": [2005736, 1754878, 1266649, 890099, 778695, 698079, 679722, 657942, 646989, 632039]}, "potential-reach-55-64": {"labels": ["groenlinks", "nederland", "kabinet", "tijd", "laten", "natuur", "jaar", "willen", "daar", "komt"], "data": [19357131, 12078147, 9244454, 7872823, 7037574, 6544140, 6401396, 6262634, 6159410, 5995691]}, "occurrences-65+": {"labels": ["groenlinks", "nederland", "samen", "tijd", "#meertoekomst", "tweede", "jaar", "#meergroenlinks", "idee", "samenleving"], "data": [477, 183, 111, 111, 110, 107, 106, 99, 94, 84]}, "impressions-65+": {"labels": ["groenlinks", "plannen", "nederland", "kabinet", "tijd", "laat", "iets", "zien", "tussen", "jesse"], "data": [1001966, 559627, 487025, 484422, 478962, 439292, 379574, 353687, 347691, 329191]}, "potential-reach-65+": {"labels": ["groenlinks", "tijd", "kabinet", "willen", "nederland", "samenleving", "zien", "beleid", "laten", "waar"], "data": [14793348, 5411216, 4419199, 4368682, 4104502, 4011581, 3901976, 3885310, 3865275, 3824371]}, "occurrences-drenthe": {"labels": ["groenlinks", "nederland", "samen", "tijd", "#meertoekomst", "tweede", "jaar", "#meergroenlinks", "idee", "samenleving"], "data": [477, 183, 111, 111, 110, 107, 106, 99, 94, 84]}, "impressions-drenthe": {"labels": ["groenlinks", "nederland", "kabinet", "tijd", "laten", "#meergroenlinks", "zien", "tegen", "klimaat", "zorgen"], "data": [324618, 292604, 202033, 165799, 126039, 117111, 113877, 113368, 111682, 110631]}, "potential-reach-drenthe": {"labels": ["groenlinks", "nederland", "willen", "tijd", "laten", "kabinet", "referendum", "tweede", "daar", "jaar"], "data": [3412961, 2393693, 1797843, 1672225, 1590085, 1550937, 1485322, 1453388, 1185284, 1182154]}, "occurrences-flevoland": {"labels": ["groenlinks", "nederland", "samen", "tijd", "#meertoekomst", "tweede", "jaar", "#meergroenlinks", "idee", "samenleving"], "data": [477, 183, 111, 111, 110, 107, 106, 99, 94, 84]}, "impressions-flevoland": {"labels": ["groenlinks", "nederland", "tijd", "kabinet", "#meergroenlinks", "iets", "samen", "#meertoekomst", "laten", "tegen"], "data": [256330, 229428, 118622, 117662, 107986, 102976, 102969, 96350, 94555, 83006]}, "potential-reach-flevoland": {"labels": ["groenlinks", "nederland", "tijd", "samen", "laten", "stemmen", "#meertoekomst", "idee", "iets", "klimaat"], "data": [2976029, 1931629, 1325387, 1153425, 989562, 988998, 978463, 961793, 955070, 948859]}, "occurrences-friesland": {"labels": ["groenlinks", "nederland", "samen", "tijd", "#meertoekomst", "tweede", "jaar", "#meergroenlinks", "idee", "samenleving"], "data": [477, 183, 111, 111, 110, 107, 106, 99, 94, 84]}, "impressions-friesland": {"labels": ["groenlinks", "nederland", "kabinet", "tijd", "#meergroenlinks", "laten", "#meertoekomst", "plannen", "zien", "klimaat"], "data": [462141, 395999, 246407, 222270, 175097, 160559, 155990, 155393, 155069, 151668]}, "potential-reach-friesland": {"labels": ["groenlinks", "nederland", "tijd", "kabinet", "klimaat", "#meertoekomst", "jaar", "#meergroenlinks", "zien", "laten"], "data": [4758881, 3410851, 2400228, 1908762, 1610621, 1505589, 1493632, 1478298, 1464779, 1443297]}, "occurrences-gelderland": {"labels": ["groenlinks", "nederland", "samen", "tijd", "#meertoekomst", "tweede", "jaar", "#meergroenlinks", "idee", "samenleving"], "data": [477, 183, 111, 111, 110, 107, 106, 99, 94, 84]}, "impressions-gelderland": {"labels": ["groenlinks", "nederland", "#meergroenlinks", "kabinet", "tijd", "#meertoekomst", "plannen", "klimaat", "laten", "zien"], "data": [1541919, 1204713, 642586, 638918, 627147, 574408, 492331, 483976, 468949, 438884]}, "potential-reach-gelderland": {"labels": ["groenlinks", "nederland", "tijd", "#meertoekomst", "#meergroenlinks", "stemmen", "klimaat", "jaar", "kabinet", "idee"], "data": [17684363, 10581579, 6708096, 6249990, 6183576, 5879456, 5345642, 5020337, 4919447, 4585928]}, "occurrences-groningen": {"labels": ["groenlinks", "nederland", "samen", "tijd", "#meertoekomst", "tweede", "jaar", "#meergroenlinks", "idee", "samenleving"], "data": [477, 183, 111, 111, 110, 107, 106, 99, 94, 84]}, "impressions-groningen": {"labels": ["groenlinks", "nederland", "#meergroenlinks", "kabinet", "tijd", "#meertoekomst", "jesse", "iets", "samen", "zien"], "data": [689675, 420816, 230272, 226250, 217645, 209456, 190526, 185344, 183214, 176453]}, "potential-reach-groningen": {"labels": ["groenlinks", "nederland", "tijd", "tweede", "#meertoekomst", "willen", "#meergroenlinks", "laten", "referendum", "kabinet"], "data": [6046073, 3695900, 2226661, 2125588, 2080794, 2071209, 2042368, 1982465, 1941608, 1779726]}, "occurrences-limburg": {"labels": ["groenlinks", "nederland", "samen", "tijd", "#meertoekomst", "tweede", "jaar", "#meergroenlinks", "idee", "samenleving"], "data": [477, 183, 111, 111, 110, 107, 106, 99, 94, 84]}, "impressions-limburg": {"labels": ["groenlinks", "nederland", "kabinet", "tijd", "#meergroenlinks", "plannen", "laten", "samen", "tegen", "zien"], "data": [816099, 711864, 403286, 388016, 288483, 281382, 275006, 263358, 263017, 257454]}, "potential-reach-limburg": {"labels": ["groenlinks", "nederland", "tijd", "kabinet", "jaar", "klimaat", "#meertoekomst", "laten", "#meergroenlinks", "samen"], "data": [8356160, 5554312, 3946919, 3113058, 2811403, 2558345, 2507545, 2473125, 2465327, 2362693]}, "occurrences-noord-brabant": {"labels": ["groenlinks", "nederland", "samen", "tijd", "#meertoekomst", "tweede", "jaar", "#meergroenlinks", "idee", "samenleving"], "data": [477, 183, 111, 111, 110, 107, 106, 99, 94, 84]}, "impressions-noord-brabant": {"labels": ["groenlinks", "nederland", "kabinet", "#meergroenlinks", "tijd", "#meertoekomst", "samen", "laten", "plannen", "iets"], "data": [1751606, 1434031, 732884, 709307, 703254, 638973, 560577, 555908, 527988, 516645]}, "potential-reach-noord-brabant": {"labels": ["groenlinks", "nederland", "tijd", "samenleving", "#meertoekomst", "#meergroenlinks", "jaar", "kabinet", "waarin", "samen"], "data": [20043415, 11682251, 7395189, 6836846, 6301828, 6144501, 5651317, 5575694, 5268666, 5102561]}, "occurrences-noord-holland": {"labels": ["groenlinks", "nederland", "samen", "tijd", "#meertoekomst", "tweede", "jaar", "#meergroenlinks", "idee", "samenleving"], "data": [477, 183, 111, 111, 110, 107, 106, 99, 94, 84]}, "impressions-noord-holland": {"labels": ["groenlinks", "nederland", "#meergroenlinks", "#meertoekomst", "iets", "samen", "tijd", "jesse", "kabinet", "woningen"], "data": [2639970, 2034956, 1291286, 1183368, 988448, 940634, 886625, 823342, 807753, 802711]}, "potential-reach-noord-holland": {"labels": ["groenlinks", "nederland", "#meertoekomst", "#meergroenlinks", "tijd", "samen", "stemmen", "jaar", "idee", "iets"], "data": [25460641, 18128992, 11812715, 11263855, 9720798, 8698902, 7361799, 7287912, 7268783, 7129376]}, "occurrences-overijssel": {"labels": ["groenlinks", "nederland", "samen", "tijd", "#meertoekomst", "tweede", "jaar", "#meergroenlinks", "idee", "samenleving"], "data": [477, 183, 111, 111, 110, 107, 106, 99, 94, 84]}, "impressions-overijssel": {"labels": ["groenlinks", "nederland", "kabinet", "tijd", "#meergroenlinks", "#meertoekomst", "laten", "samen", "klimaat", "jaar"], "data": [793386, 676784, 396874, 369038, 316078, 284032, 280107, 266145, 248682, 246209]}, "potential-reach-overijssel": {"labels": ["groenlinks", "nederland", "tijd", "laten", "willen", "stemmen", "kabinet", "tweede", "idee", "samen"], "data": [8921593, 5636689, 3998811, 3686419, 3527292, 3236392, 3070753, 3045134, 2993328, 2892856]}, "occurrences-utrecht": {"labels": ["groenlinks", "nederland", "samen", "tijd", "#meertoekomst", "tweede", "jaar", "#meergroenlinks", "idee", "samenleving"], "data": [477, 183, 111, 111, 110, 107, 106, 99, 94, 84]}, "impressions-utrecht": {"labels": ["groenlinks", "nederland", "#meergroenlinks", "keuzes", "#meertoekomst", "klimaat", "samen", "kiezen", "iets", "tijd"], "data": [1192347, 840693, 513571, 489430, 477924, 456521, 398558, 379910, 372526, 364454]}, "potential-reach-utrecht": {"labels": ["groenlinks", "nederland", "stemmen", "#meertoekomst", "#meergroenlinks", "samen", "tijd", "klimaat", "tweede", "toekomst"], "data": [14646466, 8568812, 5632517, 5425004, 4817419, 4226912, 4152659, 3955456, 3949948, 3753755]}, "occurrences-zeeland": {"labels": ["groenlinks", "nederland", "samen", "tijd", "#meertoekomst", "tweede", "jaar", "#meergroenlinks", "idee", "samenleving"], "data": [477, 183, 111, 111, 110, 107, 106, 99, 94, 84]}, "impressions-zeeland": {"labels": ["groenlinks", "nederland", "kabinet", "tijd", "#meergroenlinks", "laten", "tegen", "klimaat", "zien", "#meertoekomst"], "data": [248929, 217876, 128229, 115869, 90747, 89265, 82258, 80815, 80732, 80558]}, "potential-reach-zeeland": {"labels": ["groenlinks", "nederland", "tijd", "zeeland", "alleen", "samen", "kabinet", "daar", "tweede", "natuur"], "data": [3264141, 1787956, 1256163, 1200002, 1048863, 997787, 965919, 960341, 925464, 900607]}, "occurrences-zuid-holland": {"labels": ["groenlinks", "nederland", "samen", "tijd", "#meertoekomst", "tweede", "jaar", "#meergroenlinks", "idee", "samenleving"], "data": [477, 183, 111, 111, 110, 107, 106, 99, 94, 84]}, "impressions-zuid-holland": {"labels": ["groenlinks", "nederland", "#meergroenlinks", "#meertoekomst", "tijd", "kabinet", "samen", "iets", "plannen", "laten"], "data": [3328906, 2414841, 1381335, 1312730, 1137194, 1082502, 1070456, 970072, 948173, 914785]}, "potential-reach-zuid-holland": {"labels": ["groenlinks", "nederland", "tijd", "zoetermeer", "#meertoekomst", "#meergroenlinks", "samen", "zich", "goed", "laten"], "data": [64471896, 20601231, 16225528, 14392166, 14374900, 12779101, 12390817, 11908812, 11549416, 11200188]}}